pyeconomy/__init__.py
pyeconomy/errors.py
pyeconomy/json_data.py
pyeconomy/types/__init__.py
pyeconomy/types/user.py
pyeconomy-0.1.26.dist-info/LICENSE
pyeconomy-0.1.26.dist-info/METADATA
pyeconomy-0.1.26.dist-info/WHEEL
pyeconomy-0.1.26.dist-info/top_level.txt
pyeconomy-0.1.26.dist-info/RECORD
