Metadata-Version: 2.1
Name: pyeconomy
Version: 0.1.26
Summary: A simple to use economy module
Home-page: https://github.com/konradsic/py-economy
Author: konradsic (Konrad)
Author-email: sicinskikonrad@gmail.com
License: UNKNOWN
Keywords: python,json,discord,discord-bot,cryptocurrency,economy
Platform: UNKNOWN
Classifier: Development Status :: 2 - Pre-Alpha
Classifier: Intended Audience :: Developers
Classifier: Programming Language :: Python :: 3.8
Classifier: Programming Language :: Python :: 3.9
Classifier: Programming Language :: Python :: 3.10
Classifier: Programming Language :: Python :: 3.11
Classifier: Natural Language :: English
Classifier: Operating System :: OS Independent
License-File: LICENSE
Requires-Dist: discord
Requires-Dist: typing
